django_safari_notifications/__init__.py
django_safari_notifications/apps.py
django_safari_notifications/models.py
django_safari_notifications/signals.py
django_safari_notifications/urls.py
django_safari_notifications/views.py
django_safari_notifications/migrations/0001_initial.py
django_safari_notifications/migrations/__init__.py
django_safari_notifications/templates/django_safari_notifications/base.html
django_safari_notifications-0.1.0.dist-info/DESCRIPTION.rst
django_safari_notifications-0.1.0.dist-info/METADATA
django_safari_notifications-0.1.0.dist-info/RECORD
django_safari_notifications-0.1.0.dist-info/WHEEL
django_safari_notifications-0.1.0.dist-info/metadata.json
django_safari_notifications-0.1.0.dist-info/top_level.txt
