Metadata-Version: 2.0
Name: django-safari-notifications
Version: 0.1.0
Summary: Support for Safari Push Notifications from within Django
Home-page: https://github.com/matiboy/django-safari-notifications
Author: matiboy
Author-email: mathieu@redapesolutions.com
License: MIT
Keywords: django-safari-notifications
Platform: UNKNOWN
Classifier: Development Status :: 3 - Alpha
Classifier: Framework :: Django
Classifier: Framework :: Django :: 1.8
Classifier: Framework :: Django :: 1.9
Classifier: Framework :: Django :: 1.10
Classifier: Intended Audience :: Developers
Classifier: License :: OSI Approved :: BSD License
Classifier: Natural Language :: English
Classifier: Programming Language :: Python :: 2
Classifier: Programming Language :: Python :: 2.7
Classifier: Programming Language :: Python :: 3
Classifier: Programming Language :: Python :: 3.2
Classifier: Programming Language :: Python :: 3.3
Classifier: Programming Language :: Python :: 3.4
Classifier: Programming Language :: Python :: 3.5
Requires-Dist: django-model-utils (>=2.0)
